dsmltf/__init__.py
dsmltf/main.py
dsmltf-0.1.0.dist-info/LICENSE
dsmltf-0.1.0.dist-info/METADATA
dsmltf-0.1.0.dist-info/WHEEL
dsmltf-0.1.0.dist-info/top_level.txt
dsmltf-0.1.0.dist-info/RECORD
